Metadata-Version: 1.1
Name: smsru
Version: 0.1.0
Summary: sms.ru api library for Python
Home-page: https://github.com/gunlinux/python-smsru
Author: gunlinux
Author-email: gunlinux@ya.ru
License: GPL
Platform: UNKNOWN
Classifier: Development Status :: 4 - Beta
Classifier: Intended Audience :: Developers
Classifier: License :: OSI Approved :: GNU General Public License (GPL)
Classifier: Programming Language :: Python
Classifier: Programming Language :: Python :: 2.6
Classifier: Programming Language :: Python :: 2.7
Classifier: Programming Language :: Python :: 3.4
Classifier: Programming Language :: Python :: Implementation :: PyPy
Classifier: Topic :: Software Development :: Libraries
